icpd_core/__init__.py
icpd_core/api_client.py
icpd_core/configuration.py
icpd_core/icpd_util.py
icpd_core/rest.py
icpd_core/api/__init__.py
icpd_core/api/access_management_api.py
icpd_core/api/access_management_v3_api.py
icpd_core/api/account_management_api.py
icpd_core/api/add_on_manager_api.py
icpd_core/api/authorization_api.py
icpd_core/api/boilerplates_api.py
icpd_core/api/branding_api.py
icpd_core/api/cache_api.py
icpd_core/api/common_cloudpak_api.py
icpd_core/api/connections_api.py
icpd_core/api/custom_card_api.py
icpd_core/api/dataplanes_api.py
icpd_core/api/datarequest_api.py
icpd_core/api/deployment_manager_api.py
icpd_core/api/diagnostics_api.py
icpd_core/api/drivers_api.py
icpd_core/api/edge_applications_api.py
icpd_core/api/edge_service_provider_api.py
icpd_core/api/edge_systems_api.py
icpd_core/api/evictor_api.py
icpd_core/api/ext_services_api.py
icpd_core/api/extension_points_api.py
icpd_core/api/extensions_api.py
icpd_core/api/health_check_api.py
icpd_core/api/homepage_api.py
icpd_core/api/ieam_edge_systems_api.py
icpd_core/api/images_api.py
icpd_core/api/internal_extensions_api.py
icpd_core/api/jobs_api.py
icpd_core/api/jwt_token_api.py
icpd_core/api/kubehelper_api.py
icpd_core/api/monitor_api.py
icpd_core/api/navigation_api.py
icpd_core/api/orgs_api.py
icpd_core/api/physical_locations_api.py
icpd_core/api/placeholders_api.py
icpd_core/api/platform_utils_api.py
icpd_core/api/preferences_api.py
icpd_core/api/publish_api.py
icpd_core/api/repositories_api.py
icpd_core/api/role_management_api.py
icpd_core/api/rsi_api.py
icpd_core/api/secrets_api.py
icpd_core/api/secrets_v2_api.py
icpd_core/api/service_instance_manager_v3_api.py
icpd_core/api/snippets_api.py
icpd_core/api/tab_pages_api.py
icpd_core/api/templates_api.py
icpd_core/api/translation_api.py
icpd_core/api/user_management_api.py
icpd_core/api/vaults_api.py
icpd_core/api/vaults_v2_api.py
icpd_core/api/volumes_api.py
icpd_core/models/__init__.py
icpd_core/models/add_on_identifier.py
icpd_core-0.0.22.dist-info/METADATA
icpd_core-0.0.22.dist-info/WHEEL
icpd_core-0.0.22.dist-info/licenses/LICENSE
icpd_core-0.0.22.dist-info/RECORD
