Metadata-Version: 2.1
Name: icpd_core
Version: 0.0.22
Summary: IBM CPD Core Python Client
Project-URL: Homepage, https://www.ibm.com/docs/en/cloud-paks/cp-data/4.6.x?topic=2-managing-secrets-vaults
Author-email: IBM <rahul.shinge@us.ibm.com>
License-File: LICENSE
Classifier: License :: OSI Approved :: Apache Software License
Classifier: Operating System :: OS Independent
Classifier: Programming Language :: Python :: 3
Requires-Python: >=3.7
